alpaca_pyspark/__init__.py
alpaca_pyspark/bars.py
alpaca_pyspark/common.py
alpaca_pyspark/corp_actions/__init__.py
alpaca_pyspark/corp_actions/corporate_actions.py
alpaca_pyspark/crypto/__init__.py
alpaca_pyspark/options/__init__.py
alpaca_pyspark/options/bars.py
alpaca_pyspark/stocks/__init__.py
alpaca_pyspark/stocks/bars.py
alpaca_pyspark/stocks/trades.py
alpaca_pyspark-0.1.0.dist-info/METADATA
alpaca_pyspark-0.1.0.dist-info/WHEEL
alpaca_pyspark-0.1.0.dist-info/licenses/LICENSE
alpaca_pyspark-0.1.0.dist-info/RECORD
