Metadata-Version: 2.4
Name: alpaca-pyspark
Version: 0.1.0
Summary: Import market data from Alpaca-API with PySpark
License: LICENSE
License-File: LICENSE
Author: Tristan Nixon
Author-email: tristan.nixon@example.com
Requires-Python: >=3.11,<4.0
Classifier: License :: Other/Proprietary License
Classifier: Programming Language :: Python :: 3
Classifier: Programming Language :: Python :: 3.11
Classifier: Programming Language :: Python :: 3.12
Classifier: Programming Language :: Python :: 3.13
Classifier: Programming Language :: Python :: 3.14
Requires-Dist: pandas (>=2.0.0,<3.0.0)
Requires-Dist: pyarrow (>=19.0.1,<20.0.0)
Requires-Dist: pyarrow-stubs (>=19.0.1,<20.0.0)
Requires-Dist: pyspark (>=4.0.0,<5.0.0)
Requires-Dist: requests (>=2.31.0,<3.0.0)
Requires-Dist: types-requests (>=2.31.0,<3.0.0)
